mchatx_python/__init__.py
mchatx_python/api.py
mchatx_python/download_tl.py
mchatx_python-0.0.1.dist-info/METADATA
mchatx_python-0.0.1.dist-info/WHEEL
mchatx_python-0.0.1.dist-info/entry_points.txt
mchatx_python-0.0.1.dist-info/top_level.txt
mchatx_python-0.0.1.dist-info/RECORD
