Metadata-Version: 2.1
Name: mchatx-python
Version: 0.0.1
Summary: UNKNOWN
Home-page: UNKNOWN
Author: Michael Nolan
Author-email: celegans25@gmail.com
License: UNKNOWN
Platform: UNKNOWN
Requires-Dist: requests
